dox_util/__init__.py
dox_util/extlinks.py
dox_util/linkcheck.py
dox_util/rule.py
dox_util/source.py
dox_util/toctree.py
dox_util/todo.py
dox_util/version.py
dox_util/weak.py
dox_util/_static/dox_util_colors.css
dox_util-0.1.0.dist-info/LICENSE
dox_util-0.1.0.dist-info/METADATA
dox_util-0.1.0.dist-info/WHEEL
dox_util-0.1.0.dist-info/top_level.txt
dox_util-0.1.0.dist-info/RECORD
